rustpycoils.pypy36-pp73-darwin.so
rustpycoils-0.1.0.dist-info/LICENSE
rustpycoils-0.1.0.dist-info/METADATA
rustpycoils-0.1.0.dist-info/WHEEL
rustpycoils-0.1.0.dist-info/top_level.txt
rustpycoils-0.1.0.dist-info/RECORD
