Metadata-Version: 2.1
Name: rustpycoils
Version: 0.1.0
Summary: Off-axis magnetic fields for coils and solenoids
Home-page: http://github.com/jdrtommey/rustpycoils/
Author: J.D.R. Tommey
Author-email: jake@tommey.co.uk
License: MIT
Platform: UNKNOWN
Classifier: Development Status :: 3 - Alpha
Classifier: Programming Language :: Python :: 3
Classifier: Intended Audience :: Science/Research
Classifier: License :: OSI Approved :: MIT License
Classifier: Topic :: Software Development :: Libraries
Classifier: Topic :: Utilities
License-File: LICENSE
